pypega/__init__.py
pypega/environment.py
pypega-0.0.55.dist-info/LICENSE
pypega-0.0.55.dist-info/WHEEL
pypega-0.0.55.dist-info/METADATA
pypega-0.0.55.dist-info/RECORD
