Metadata-Version: 2.1
Name: pypega
Version: 0.0.55
Summary: Python package for orchestrating Pega environments
License: LICENSE
Keywords: pega,bpm,pypega
Author: Rob Smart
Author-email: rob.smart@pega.com
Maintainer: Rob Smart
Maintainer-email: rob.smart@pega.com
Classifier: License :: Other/Proprietary License
Classifier: Operating System :: OS Independent
Classifier: Programming Language :: Python :: 2
Classifier: Programming Language :: Python :: 2.7
Classifier: Programming Language :: Python :: 3
Classifier: Programming Language :: Python :: 3.4
Classifier: Programming Language :: Python :: 3.5
Classifier: Programming Language :: Python :: 3.6
Classifier: Programming Language :: Python :: 3.7
Classifier: Programming Language :: Python :: 3.8
Classifier: Programming Language :: Python :: 3.9
Classifier: Programming Language :: Python :: 3.10
Classifier: Programming Language :: Python :: 3.11
Classifier: Programming Language :: Python :: 3
Requires-Dist: requests-oauthlib (>=1.3.0,<2.0.0)
